setup.py
nvhead/__init__.py
nvhead/common.py
nvhead/consts.py
nvhead/head.py
nvhead/specific.py
nvhead.egg-info/PKG-INFO
nvhead.egg-info/SOURCES.txt
nvhead.egg-info/dependency_links.txt
nvhead.egg-info/top_level.txt